ggpyparser/__init__.py
ggpyparser/liquipedia_objects/__init__.py
ggpyparser/liquipedia_objects/liquipedia_page.py
ggpyparser/liquipedia_objects/player.py
ggpyparser/liquipedia_objects/team.py
ggpyparser/liquipedia_objects/tournament.py
ggpyparser/parse_liquipedia/__init__.py
ggpyparser/parse_liquipedia/parse_general_pages.py
ggpyparser/parse_liquipedia/parse_liquipedia_html.py
ggpyparser/parse_liquipedia/parse_liquipedia_wc.py
ggpyparser/parse_liquipedia/parse_multiple_liquipedia_pages.py
ggpyparser-0.0.6.dist-info/METADATA
ggpyparser-0.0.6.dist-info/WHEEL
ggpyparser-0.0.6.dist-info/licenses/LICENSE
ggpyparser-0.0.6.dist-info/RECORD
