Metadata-Version: 2.4
Name: ggpyparser
Version: 0.0.6
Summary: Python based liquipedia esports data scraper 
Project-URL: Homepage, https://github.com/Lou-Zhou/gg-pyparser
Project-URL: Issues, https://github.com/Lou-Zhou/gg-pyparser/issues
Author: Lou Zhou
License-Expression: MIT
License-File: LICENSE
Requires-Python: >=3.9
Requires-Dist: beautifulsoup4>=4.12
Requires-Dist: mwparserfromhell>=0.6
Requires-Dist: pandas>=2.0
Requires-Dist: requests>=2.31
